LICENSE
MANIFEST.in
README.md
requirements.txt
setup.py
bin/compile-manifest-from-veba.py
bin/leviathan-index.py
bin/leviathan-info.py
bin/leviathan-merge.py
bin/leviathan-preprocess.py
bin/leviathan-profile-pathway.py
bin/leviathan-profile-taxonomy.py
leviathan/__init__.py
leviathan/index.py
leviathan/profile_pathway.py
leviathan/profile_taxonomy.py
leviathan/utils.py
leviathan.egg-info/PKG-INFO
leviathan.egg-info/SOURCES.txt
leviathan.egg-info/dependency_links.txt
leviathan.egg-info/requires.txt
leviathan.egg-info/top_level.txt