Metadata-Version: 2.1
Name: leviathan
Version: 2025.7.4
Summary: Genome-resolved taxonomic and pathway profiling
Home-page: https://github.com/new-atlantis-labs/leviathan
Author: Josh L. Espinoza
Author-email: jolespin@newatlantis.io, jol.espinoz@gmail.com
License: MIT
License-File: LICENSE
Requires-Dist: pathlib
Requires-Dist: tqdm
Requires-Dist: memory_profiler
Requires-Dist: pandas
Requires-Dist: pyfastx
Requires-Dist: networkx
Requires-Dist: scipy
Requires-Dist: kegg_pathway_profiler>=2024.9.21
Requires-Dist: pyexeggutor>=2024.11.18
Requires-Dist: fastparquet
Requires-Dist: xarray
Requires-Dist: h5netcdf
